odt2csv/__init__.py
odt2csv/__main__.py
odt2csv/exceptions.py
odt2csv-0.1.dist-info/licenses/LICENSE
odt2csv-0.1.dist-info/METADATA
odt2csv-0.1.dist-info/WHEEL
odt2csv-0.1.dist-info/top_level.txt
odt2csv-0.1.dist-info/RECORD
