Metadata-Version: 2.4
Name: odt2csv
Version: 0.1
Summary: Converts an OOMMF data table (ODT) file generated by OOMMF simulations into a CSV data file for better compatibility with modern applications
Home-page: https://github.com/groaking/odt2csv
Author: Samarthya Lykamanuella
Author-email: lykamanuella@outlook.com
Maintainer: Samarthya Lykamanuella
Maintainer-email: lykamanuella@outlook.com
License: GNU General Public License v3.0 or later
Project-URL: Bug Reports, https://github.com/groaking/odt2csv/issues
Project-URL: GitHub, https://github.com/groaking/odt2csv
Project-URL: Home Page, https://github.com/groaking/odt2csv
Project-URL: Change Log, https://github.com/groaking/odt2csv/blob/main/CHANGELOG.md
Keywords: oommf,odt,csv,conversion,tools,datatable,simulation,micromagnetic,nanomagnetic,physics,magnetism
Classifier: Development Status :: 3 - Alpha
Classifier: Intended Audience :: Education
Classifier: Intended Audience :: Science/Research
Classifier: Topic :: Scientific/Engineering :: Physics
Classifier: Topic :: Software Development :: Libraries
Classifier: Topic :: Utilities
Classifier: License :: OSI Approved :: GNU General Public License v3 or later (GPLv3+)
Classifier: Programming Language :: Python :: 3
Classifier: Programming Language :: Python :: 3.8
Classifier: Programming Language :: Python :: 3.9
Classifier: Programming Language :: Python :: 3.10
Classifier: Programming Language :: Python :: 3.11
Classifier: Programming Language :: Python :: 3.12
Classifier: Programming Language :: Python :: 3.13
Classifier: Programming Language :: Python :: 3.14
Classifier: Environment :: Console
Requires-Python: >=3.8
License-File: LICENSE
Dynamic: author
Dynamic: author-email
Dynamic: classifier
Dynamic: description
Dynamic: description-content-type
Dynamic: home-page
Dynamic: keywords
Dynamic: license
Dynamic: license-file
Dynamic: maintainer
Dynamic: maintainer-email
Dynamic: project-url
Dynamic: requires-python
Dynamic: summary
